odoo/addons/web_widget_bokeh_chart/README.rst
odoo/addons/web_widget_bokeh_chart/__init__.py
odoo/addons/web_widget_bokeh_chart/__manifest__.py
odoo/addons/web_widget_bokeh_chart/i18n/web_widget_bokeh_chart.pot
odoo/addons/web_widget_bokeh_chart/static/description/example.png
odoo/addons/web_widget_bokeh_chart/static/description/icon.png
odoo/addons/web_widget_bokeh_chart/static/src/js/web_widget_bokeh_chart.js
odoo/addons/web_widget_bokeh_chart/static/src/less/custom-bokeh.less
odoo/addons/web_widget_bokeh_chart/static/src/lib/bokeh/bokeh-0.12.7.css
odoo/addons/web_widget_bokeh_chart/static/src/lib/bokeh/bokeh-0.12.7.js
odoo/addons/web_widget_bokeh_chart/static/src/lib/bokeh/bokeh-widgets-0.12.7.css
odoo/addons/web_widget_bokeh_chart/static/src/lib/bokeh/bokeh-widgets-0.12.7.js
odoo/addons/web_widget_bokeh_chart/views/web_widget_bokeh_chart.xml
odoo11_addon_web_widget_bokeh_chart-11.0.1.1.1.dist-info/METADATA
odoo11_addon_web_widget_bokeh_chart-11.0.1.1.1.dist-info/WHEEL
odoo11_addon_web_widget_bokeh_chart-11.0.1.1.1.dist-info/top_level.txt
odoo11_addon_web_widget_bokeh_chart-11.0.1.1.1.dist-info/RECORD
